[
  {
    "id":"yourock",
    "name":"YOU ROCK.",
    "requirements":[
      {
        "type":"POPULATION",
        "amount":10
      }
    ],
    "rewards":[
      {
        "type":"GIVE",
        "thing":"MONEY",
        "amount":1000
      }
    ]
  },
  {
    "id":"build1hotelroom",
    "name":"Build 3 Hotel Rooms.",
    "requirements":[
      {
        "type":"BUILD",
        "thing":"HOTEL_ROOM",
        "amount":3
      }
    ],
    "rewards":[
      {
        "type":"UNLOCK",
        "thing":"MAIDS_OFFICE"
      }
    ]
  },
  {
    "id":"build3commercialspaces",
    "name":"Build 3 Commercial Spaces.",
    "requirements":[
      {
        "type":"BUILD",
        "thing":"COMMERCIAL_SPACE",
        "amount":3
      }
    ],
    "rewards":[
      {
        "type":"UNLOCK",
        "thing":"JANITORS_CLOSET"
      }
    ]
  }
]
